psa_utils/__init__.py
psa_utils/common.py
psa_utils/download.py
psa_utils/geogen.py
psa_utils/internal.py
psa_utils/packager.py
psa_utils/pdap.py
psa_utils/tap.py
psa_utils-0.3.post0.dist-info/licenses/LICENSE
psa_utils-0.3.post0.dist-info/METADATA
psa_utils-0.3.post0.dist-info/WHEEL
psa_utils-0.3.post0.dist-info/top_level.txt
psa_utils-0.3.post0.dist-info/RECORD
