Metadata-Version: 2.4
Name: psa_utils
Version: 0.3.post0
Summary: A collection of PSA utilities
Keywords: PDS,PDS4,archive,data,PSA,ESA
Requires-Python: >=3.10
License-File: LICENSE
Requires-Dist: pandas
Requires-Dist: pyyaml
Requires-Dist: astropy
Requires-Dist: pyvo
Requires-Dist: numpy
Requires-Dist: lxml
Requires-Dist: matplotlib
Requires-Dist: requests
Requires-Dist: astroquery
Requires-Dist: pds4_utils>=0.2
Dynamic: license-file
